poroscleanlit/__init__.py
poroscleanlit/__main__.py
poroscleanlit/citation_rules.py
poroscleanlit/config.py
poroscleanlit/document_numbering_rules.py
poroscleanlit/greek_latex_converter.py
poroscleanlit/patterns.py
poroscleanlit/plugin_system.py
poroscleanlit/py.typed
poroscleanlit/text_cleaner.py
poroscleanlit/unicode_norm.py
poroscleanlit/utils.py
poroscleanlit/examples/basic_usage.py
poroscleanlit/examples/test_latex_math_spaces_md_json.py
poroscleanlit/examples/test_latex_space_example.py
poroscleanlit-0.2.0.dist-info/METADATA
poroscleanlit-0.2.0.dist-info/WHEEL
poroscleanlit-0.2.0.dist-info/entry_points.txt
poroscleanlit-0.2.0.dist-info/top_level.txt
poroscleanlit-0.2.0.dist-info/RECORD
